django_sys_indicator/__init__.py
django_sys_indicator/apps.py
django_sys_indicator/conf.py
django_sys_indicator/middleware.py
django_sys_indicator/py.typed
django_sys_indicator/utils.py
django_sys_indicator/templates/django_sys_indicator/system_indicator.html
django_sys_indicator-2.2.0.dist-info/LICENSE
django_sys_indicator-2.2.0.dist-info/METADATA
django_sys_indicator-2.2.0.dist-info/WHEEL
django_sys_indicator-2.2.0.dist-info/top_level.txt
django_sys_indicator-2.2.0.dist-info/RECORD
