Metadata-Version: 2.1
Name: django-sys-indicator
Version: 2.2.0
Summary: A system/environment indicator for django.
Author-email: Mark Walker <theshow@gmail.com>
Project-URL: Changelog, https://github.com/marksweb/django-sys-indicator/HISTORY.rst
Project-URL: Repository, https://github.com/marksweb/django-sys-indicator
Keywords: Django
Classifier: Development Status :: 5 - Production/Stable
Classifier: Framework :: Django :: 3.2
Classifier: Framework :: Django :: 4.0
Classifier: Framework :: Django :: 4.1
Classifier: Framework :: Django :: 4.2
Classifier: Framework :: Django :: 5.0
Classifier: Framework :: Django :: 5.1
Classifier: Framework :: IPython
Classifier: Intended Audience :: Developers
Classifier: License :: OSI Approved :: MIT License
Classifier: Natural Language :: English
Classifier: Operating System :: OS Independent
Classifier: Programming Language :: Python :: 3 :: Only
Classifier: Programming Language :: Python :: 3.8
Classifier: Programming Language :: Python :: 3.9
Classifier: Programming Language :: Python :: 3.10
Classifier: Programming Language :: Python :: 3.11
Classifier: Programming Language :: Python :: 3.12
Classifier: Programming Language :: Python :: 3.13
Classifier: Programming Language :: Python :: Implementation :: CPython
Requires-Python: >=3.8
License-File: LICENSE
Requires-Dist: django >=3.2
